druta/__init__.py
druta/video_dataset.py
druta-0.0.2.dist-info/METADATA
druta-0.0.2.dist-info/WHEEL
druta-0.0.2.dist-info/top_level.txt
druta-0.0.2.dist-info/RECORD
