Metadata-Version: 2.4
Name: druta
Version: 0.0.2
Summary: druta (द्रुत) - A fast video dataset format for PyTorch (for when storage isn't a problem)
Home-page: https://github.com/mayukhdeb/druta
Author: mayukhdeb
Author-email: mayukhmainak2000@gmail.com
Classifier: Programming Language :: Python :: 3
Classifier: Operating System :: OS Independent
Requires-Dist: decord2
Requires-Dist: torch
Requires-Dist: tqdm
Requires-Dist: torchtyping
Dynamic: author
Dynamic: author-email
Dynamic: classifier
Dynamic: description
Dynamic: description-content-type
Dynamic: home-page
Dynamic: requires-dist
Dynamic: summary
